mathz/__init__.py
mathz/main.py
mathz-0.1.0.dist-info/LICENSE
mathz-0.1.0.dist-info/METADATA
mathz-0.1.0.dist-info/WHEEL
mathz-0.1.0.dist-info/entry_points.txt
mathz-0.1.0.dist-info/top_level.txt
mathz-0.1.0.dist-info/RECORD
