Metadata-Version: 2.1
Name: mathz
Version: 0.1.0
Summary: A example Python package
Home-page: https://github.com/shuds13/pyexample
Author: Stephen Hudson
Author-email: icodernet@gmail.com
License: BSD 2-clause
Platform: UNKNOWN
Classifier: Development Status :: 1 - Planning
Classifier: Intended Audience :: Science/Research
Classifier: License :: OSI Approved :: BSD License
Classifier: Operating System :: POSIX :: Linux
Classifier: Programming Language :: Python :: 2
Classifier: Programming Language :: Python :: 2.7
Classifier: Programming Language :: Python :: 3
Classifier: Programming Language :: Python :: 3.4
Classifier: Programming Language :: Python :: 3.5
License-File: LICENSE
Requires-Dist: aiogram >=2.25
Requires-Dist: Pillow >=10.0.0
Requires-Dist: pynput
